intenzclient/__init__.py
intenzclient/auth.py
intenzclient/client.py
intenzclient/exceptions.py
intenzclient/resources.py
intenzclient/valo.py
intenzclient-0.2.0.dist-info/licenses/LICENSE
intenzclient-0.2.0.dist-info/METADATA
intenzclient-0.2.0.dist-info/WHEEL
intenzclient-0.2.0.dist-info/top_level.txt
intenzclient-0.2.0.dist-info/RECORD
