Metadata-Version: 2.4
Name: intenzclient
Version: 0.2.0
Summary: Python client for Valorant internal APIs
Author: intenzdev
License: MIT
Project-URL: Source, https://github.com/inntenz/intenzclient
Requires-Python: >=3.8
License-File: LICENSE
Requires-Dist: requests
Requires-Dist: urllib3
Dynamic: license-file
